{
  "suites": [
    {
      "name": "Report 1",
      "path": "report1"
    },
    {
      "name": "Report 2",
      "path": "report2"
    },
    {
      "name": "Report 3",
      "path": "report3"
    },
    {
      "name": "Report 4",
      "path": "report4"
    },
    {
      "name": "Report 5",
      "path": "report5"
    },
    {
      "name": "Report 6",
      "path": "report6"
    },
    {
      "name": "2024-12-12T15:24:03",
      "path": "12299423021"
    },
    {
      "name": "2024-12-18T05:10:51",
      "path": "12386757444"
    },
    {
      "name": "2025-02-01T05:23:37",
      "path": "13085548333"
    },
    {
      "name": "2025-02-01T05:23:46",
      "path": "13085549946"
    },
    {
      "name": "2025-02-01T05:23:59",
      "path": "13085551026"
    },
    {
      "name": "2025-02-28T09:22:18",
      "path": "13585056640"
    },
    {
      "name": "2025-02-28T09:22:31",
      "path": "13585060062"
    },
    {
      "name": "2025-03-12T09:23:26",
      "path": "13807834138"
    },
    {
      "name": "2025-03-12T09:24:19",
      "path": "13807852321"
    },
    {
      "name": "2025-05-31T12:02:43",
      "path": "15363436980"
    },
    {
      "name": "2025-06-22T09:31:43",
      "path": "15805148766"
    },
    {
      "name": "2025-06-22T09:31:47",
      "path": "15805147216"
    },
    {
      "name": "2025-06-29T05:28:49",
      "path": "15951915396"
    },
    {
      "name": "2025-06-29T05:29:07",
      "path": "15951916274"
    },
    {
      "name": "2025-06-29T05:29:13",
      "path": "15951917855"
    },
    {
      "name": "2025-09-20T14:17:29",
      "path": "17880912596"
    },
    {
      "name": "2025-09-20T15:59:25",
      "path": "17881869981"
    },
    {
      "name": "2025-09-29T07:00:54",
      "path": "18088547981"
    },
    {
      "name": "2025-10-08T12:06:01",
      "path": "18343964232"
    },
    {
      "name": "2025-10-08T12:06:07",
      "path": "18343968071"
    },
    {
      "name": "2025-10-08T12:06:13",
      "path": "18343972011"
    },
    {
      "name": "2025-10-08T12:06:14",
      "path": "18343976338"
    }
  ]
}
