{"id":"55c04a2d18a6c32cf5ca2e03942bb51d024ae49f","version":1,"className":"io.github.vooft.pepper.sample.LotOfStepsPepperSpec","name":"my test scenario","tags":[],"steps":[{"id":"76d176eec509112bbf4826f64722a542a2b4eb92","prefix":"GIVEN","index":0,"name":"generate random string","status":"PASSED","arguments":[{"name":"prefix","type":"kotlin.String","value":"first"}],"result":"first -1797794156","error":null,"startedAt":"2025-11-30T16:17:44.366763847Z","finishedAt":"2025-11-30T16:17:44.385290507Z"},{"id":"76d176eec509112bbf4826f64722a542a2b4eb92","prefix":"GIVEN","index":1,"name":"generate random string","status":"PASSED","arguments":[{"name":"prefix","type":"kotlin.String","value":"second"}],"result":"second -1964179173","error":null,"startedAt":"2025-11-30T16:17:44.386328380Z","finishedAt":"2025-11-30T16:17:44.394662424Z"},{"id":"944007ae5d56a056c754860f21efa03075ae0dab","prefix":"WHEN","index":2,"name":"two strings are compared","status":"PASSED","arguments":[{"name":"first","type":"kotlin.String","value":"first -1797794156"},{"name":"second","type":"kotlin.String","value":"second -1964179173"}],"result":"CompareResult(first=first -1797794156, second=second -1964179173, result=false)","error":null,"startedAt":"2025-11-30T16:17:44.396193711Z","finishedAt":"2025-11-30T16:17:44.408590606Z"},{"id":"f3b27ba8355644ef329dbd7d879320f54d3441c2","prefix":"THEN","index":3,"name":"compare result is 'false'","status":"PASSED","arguments":[{"name":"compareResult","type":"io.github.vooft.pepper.sample.CompareResult","value":"CompareResult(first=first -1797794156, second=second -1964179173, result=false)"},{"name":"expected","type":"kotlin.Boolean","value":"false"}],"result":"kotlin.Unit","error":null,"startedAt":"2025-11-30T16:17:44.409633619Z","finishedAt":"2025-11-30T16:17:44.415434648Z"},{"id":"f3b27ba8355644ef329dbd7d879320f54d3441c2","prefix":"THEN","index":4,"name":"compare result is 'false'","status":"PASSED","arguments":[{"name":"compareResult","type":"io.github.vooft.pepper.sample.CompareResult","value":"CompareResult(first=first -1797794156, second=second -1964179173, result=false)"},{"name":"expected","type":"kotlin.Boolean","value":"false"}],"result":"kotlin.Unit","error":null,"startedAt":"2025-11-30T16:17:44.418129312Z","finishedAt":"2025-11-30T16:17:44.427009104Z"},{"id":"f3b27ba8355644ef329dbd7d879320f54d3441c2","prefix":"THEN","index":5,"name":"compare result is 'false'","status":"PASSED","arguments":[{"name":"compareResult","type":"io.github.vooft.pepper.sample.CompareResult","value":"CompareResult(first=first -1797794156, second=second -1964179173, result=false)"},{"name":"expected","type":"kotlin.Boolean","value":"false"}],"result":"kotlin.Unit","error":null,"startedAt":"2025-11-30T16:17:44.427803541Z","finishedAt":"2025-11-30T16:17:44.442868691Z"},{"id":"f3b27ba8355644ef329dbd7d879320f54d3441c2","prefix":"THEN","index":6,"name":"compare result is 'false'","status":"PASSED","arguments":[{"name":"compareResult","type":"io.github.vooft.pepper.sample.CompareResult","value":"CompareResult(first=first -1797794156, second=second -1964179173, result=false)"},{"name":"expected","type":"kotlin.Boolean","value":"false"}],"result":"kotlin.Unit","error":null,"startedAt":"2025-11-30T16:17:44.443907475Z","finishedAt":"2025-11-30T16:17:44.467770635Z"},{"id":"f3b27ba8355644ef329dbd7d879320f54d3441c2","prefix":"THEN","index":7,"name":"compare result is 'false'","status":"PASSED","arguments":[{"name":"compareResult","type":"io.github.vooft.pepper.sample.CompareResult","value":"CompareResult(first=first -1797794156, second=second -1964179173, result=false)"},{"name":"expected","type":"kotlin.Boolean","value":"false"}],"result":"kotlin.Unit","error":null,"startedAt":"2025-11-30T16:17:44.468684816Z","finishedAt":"2025-11-30T16:17:44.476550740Z"},{"id":"f3b27ba8355644ef329dbd7d879320f54d3441c2","prefix":"THEN","index":8,"name":"compare result is 'false'","status":"PASSED","arguments":[{"name":"compareResult","type":"io.github.vooft.pepper.sample.CompareResult","value":"CompareResult(first=first -1797794156, second=second -1964179173, result=false)"},{"name":"expected","type":"kotlin.Boolean","value":"false"}],"result":"kotlin.Unit","error":null,"startedAt":"2025-11-30T16:17:44.477388118Z","finishedAt":"2025-11-30T16:17:44.487561851Z"},{"id":"f3b27ba8355644ef329dbd7d879320f54d3441c2","prefix":"THEN","index":9,"name":"compare result is 'false'","status":"PASSED","arguments":[{"name":"compareResult","type":"io.github.vooft.pepper.sample.CompareResult","value":"CompareResult(first=first -1797794156, second=second -1964179173, result=false)"},{"name":"expected","type":"kotlin.Boolean","value":"false"}],"result":"kotlin.Unit","error":null,"startedAt":"2025-11-30T16:17:44.488487615Z","finishedAt":"2025-11-30T16:17:44.496777061Z"},{"id":"f3b27ba8355644ef329dbd7d879320f54d3441c2","prefix":"THEN","index":10,"name":"compare result is 'false'","status":"PASSED","arguments":[{"name":"compareResult","type":"io.github.vooft.pepper.sample.CompareResult","value":"CompareResult(first=first -1797794156, second=second -1964179173, result=false)"},{"name":"expected","type":"kotlin.Boolean","value":"false"}],"result":"kotlin.Unit","error":null,"startedAt":"2025-11-30T16:17:44.499583886Z","finishedAt":"2025-11-30T16:17:44.506579727Z"},{"id":"f3b27ba8355644ef329dbd7d879320f54d3441c2","prefix":"THEN","index":11,"name":"compare result is 'false'","status":"PASSED","arguments":[{"name":"compareResult","type":"io.github.vooft.pepper.sample.CompareResult","value":"CompareResult(first=first -1797794156, second=second -1964179173, result=false)"},{"name":"expected","type":"kotlin.Boolean","value":"false"}],"result":"kotlin.Unit","error":null,"startedAt":"2025-11-30T16:17:44.507604585Z","finishedAt":"2025-11-30T16:17:44.512093959Z"},{"id":"f3b27ba8355644ef329dbd7d879320f54d3441c2","prefix":"THEN","index":12,"name":"compare result is 'false'","status":"PASSED","arguments":[{"name":"compareResult","type":"io.github.vooft.pepper.sample.CompareResult","value":"CompareResult(first=first -1797794156, second=second -1964179173, result=false)"},{"name":"expected","type":"kotlin.Boolean","value":"false"}],"result":"kotlin.Unit","error":null,"startedAt":"2025-11-30T16:17:44.512855765Z","finishedAt":"2025-11-30T16:17:44.522321874Z"},{"id":"f3b27ba8355644ef329dbd7d879320f54d3441c2","prefix":"THEN","index":13,"name":"compare result is 'false'","status":"PASSED","arguments":[{"name":"compareResult","type":"io.github.vooft.pepper.sample.CompareResult","value":"CompareResult(first=first -1797794156, second=second -1964179173, result=false)"},{"name":"expected","type":"kotlin.Boolean","value":"false"}],"result":"kotlin.Unit","error":null,"startedAt":"2025-11-30T16:17:44.524432846Z","finishedAt":"2025-11-30T16:17:44.531113956Z"},{"id":"f3b27ba8355644ef329dbd7d879320f54d3441c2","prefix":"THEN","index":14,"name":"compare result is 'false'","status":"PASSED","arguments":[{"name":"compareResult","type":"io.github.vooft.pepper.sample.CompareResult","value":"CompareResult(first=first -1797794156, second=second -1964179173, result=false)"},{"name":"expected","type":"kotlin.Boolean","value":"false"}],"result":"kotlin.Unit","error":null,"startedAt":"2025-11-30T16:17:44.534543413Z","finishedAt":"2025-11-30T16:17:44.538113879Z"}],"startedAt":"2025-11-30T16:17:44.365754027Z","finishedAt":"2025-11-30T16:17:44.538723641Z"}